LICENSE
MANIFEST.in
README.md
setup.py
Geometry3D/__init__.py
Geometry3D.egg-info/PKG-INFO
Geometry3D.egg-info/SOURCES.txt
Geometry3D.egg-info/dependency_links.txt
Geometry3D.egg-info/top_level.txt
Geometry3D/calc/__init__.py
Geometry3D/calc/acute.py
Geometry3D/calc/angle.py
Geometry3D/calc/aux_calc.py
Geometry3D/calc/distance.py
Geometry3D/calc/intersection.py
Geometry3D/calc/volume.py
Geometry3D/geometry/__init__.py
Geometry3D/geometry/body.py
Geometry3D/geometry/halfline.py
Geometry3D/geometry/line.py
Geometry3D/geometry/plane.py
Geometry3D/geometry/point.py
Geometry3D/geometry/polygon.py
Geometry3D/geometry/polyhedron.py
Geometry3D/geometry/pyramid.py
Geometry3D/geometry/segment.py
Geometry3D/utils/__init__.py
Geometry3D/utils/constant.py
Geometry3D/utils/logger.py
Geometry3D/utils/solver.py
Geometry3D/utils/util.py
Geometry3D/utils/vector.py
Geometry3D/visualization/__init__.py
Geometry3D/visualization/arrow.py
Geometry3D/visualization/base_visualizer.py
Geometry3D/visualization/visualizer.py
Geometry3D/visualization/visualizer_matplotlib.py
Geometry3D/visualization/visualizer_open3d.py